shine/LICENSE
shine/__init__.py
shine/private.pem
shine/svnversion.cpython-37m-x86_64-linux-gnu.so
shine/svnversion_io.cpython-37m-x86_64-linux-gnu.so
shine/units.cpython-37m-x86_64-linux-gnu.so
shine/version.cpython-37m-x86_64-linux-gnu.so
shine/__pycache__/__init__.cpython-37.pyc
shine/dft/__init__.py
shine/dft/arraydict.cpython-37m-x86_64-linux-gnu.so
shine/dft/aseinterface.cpython-37m-x86_64-linux-gnu.so
shine/dft/basis_data.cpython-37m-x86_64-linux-gnu.so
shine/dft/density.cpython-37m-x86_64-linux-gnu.so
shine/dft/dipole_correction.cpython-37m-x86_64-linux-gnu.so
shine/dft/domain.cpython-37m-x86_64-linux-gnu.so
shine/dft/fd_operators.cpython-37m-x86_64-linux-gnu.so
shine/dft/forces.cpython-37m-x86_64-linux-gnu.so
shine/dft/gaunt.cpython-37m-x86_64-linux-gnu.so
shine/dft/grid_descriptor.cpython-37m-x86_64-linux-gnu.so
shine/dft/hamiltonian.cpython-37m-x86_64-linux-gnu.so
shine/dft/hs_operators.cpython-37m-x86_64-linux-gnu.so
shine/dft/kpoint.cpython-37m-x86_64-linux-gnu.so
shine/dft/kpt_descriptor.cpython-37m-x86_64-linux-gnu.so
shine/dft/lfc.cpython-37m-x86_64-linux-gnu.so
shine/dft/localized_functions.cpython-37m-x86_64-linux-gnu.so
shine/dft/mixer.cpython-37m-x86_64-linux-gnu.so
shine/dft/occupations.cpython-37m-x86_64-linux-gnu.so
shine/dft/output.cpython-37m-x86_64-linux-gnu.so
shine/dft/overlap.cpython-37m-x86_64-linux-gnu.so
shine/dft/parameters.cpython-37m-x86_64-linux-gnu.so
shine/dft/paw.cpython-37m-x86_64-linux-gnu.so
shine/dft/poisson.cpython-37m-x86_64-linux-gnu.so
shine/dft/rotation.cpython-37m-x86_64-linux-gnu.so
shine/dft/scf.cpython-37m-x86_64-linux-gnu.so
shine/dft/setup.cpython-37m-x86_64-linux-gnu.so
shine/dft/setup_data.cpython-37m-x86_64-linux-gnu.so
shine/dft/spherical_harmonics.cpython-37m-x86_64-linux-gnu.so
shine/dft/spline.cpython-37m-x86_64-linux-gnu.so
shine/dft/stress.cpython-37m-x86_64-linux-gnu.so
shine/dft/symmetry.cpython-37m-x86_64-linux-gnu.so
shine/dft/transformers.cpython-37m-x86_64-linux-gnu.so
shine_package-1.0.4.dist-info/METADATA
shine_package-1.0.4.dist-info/WHEEL
shine_package-1.0.4.dist-info/top_level.txt
shine_package-1.0.4.dist-info/RECORD
