Metadata-Version: 2.1
Name: shine-package
Version: 1.0.4
Summary: This is a first-principle calcluation package based on atomic orbital DFT
Home-page: https://github.com/IamRocketSwallow/shine
Author: jingzhe
Author-email: jingzhe@tianyan3d.com
License: Proprietary
Platform: linux
Classifier: Operating System :: OS Independent
Classifier: Intended Audience :: Developers
Classifier: Programming Language :: Python :: 3.7
Classifier: Topic :: Software Development :: Libraries
